zensols/zotsite/resources/app.conf
zensols/zotsite/resources/default.conf
zensols/zotsite/resources/obj.conf
zensols/zotsite/resources/zotero.sql
zensols/zotsite/resources/site/lib/css/bootstrap-3-retro.css
zensols/zotsite/resources/site/lib/css/bootstrap-treeview.min.css
zensols/zotsite/resources/site/lib/css/bootstrap.min.css
zensols/zotsite/resources/site/lib/css/bootstrap.min.css.map
zensols/zotsite/resources/site/lib/css/datatables.css
zensols/zotsite/resources/site/lib/css/datatables.min.css
zensols/zotsite/resources/site/lib/css/zotero.css
zensols/zotsite/resources/site/lib/fonts/glyphicons-halflings-regular.eot
zensols/zotsite/resources/site/lib/fonts/glyphicons-halflings-regular.svg
zensols/zotsite/resources/site/lib/fonts/glyphicons-halflings-regular.ttf
zensols/zotsite/resources/site/lib/fonts/glyphicons-halflings-regular.woff
zensols/zotsite/resources/site/lib/fonts/glyphicons-halflings-regular.woff2
zensols/zotsite/resources/site/lib/img/github-logo.svg
zensols/zotsite/resources/site/lib/img/zotero-logo.svg
zensols/zotsite/resources/site/lib/js/bootstrap-treeview.min.js
zensols/zotsite/resources/site/lib/js/bootstrap.min.js
zensols/zotsite/resources/site/lib/js/bootstrap.min.js.map
zensols/zotsite/resources/site/lib/js/datatables.js
zensols/zotsite/resources/site/lib/js/datatables.min.js
zensols/zotsite/resources/site/lib/js/jquery.min.js
zensols/zotsite/resources/site/lib/js/jquery.min.map
zensols/zotsite/resources/site/lib/js/popper.min.js
zensols/zotsite/resources/site/lib/js/popper.min.js.map
zensols/zotsite/resources/site/src/index.html
zensols/zotsite/resources/site/src/css/zotsite.css
zensols/zotsite/resources/site/src/js/clipboard.js
zensols/zotsite/resources/site/src/js/zotero.js
zensols/zotsite/__init__.py
zensols/zotsite/app.py
zensols/zotsite/betterbib.py
zensols/zotsite/cite.py
zensols/zotsite/cli.py
zensols/zotsite/db.py
zensols/zotsite/domain.py
zensols/zotsite/fscpvisitor.py
zensols/zotsite/itemmap.py
zensols/zotsite/navvisitor.py
zensols_zotsite-1.2.0.dist-info/METADATA
zensols_zotsite-1.2.0.dist-info/WHEEL
zensols_zotsite-1.2.0.dist-info/entry_points.txt
zensols_zotsite-1.2.0.dist-info/licenses/LICENSE.md
zensols_zotsite-1.2.0.dist-info/RECORD
