Metadata-Version: 2.3
Name: zensols_zotsite
Version: 1.2.0
Summary: This program exports your local [Zotero] library to a usable HTML website with following features.
Project-URL: Homepage, https://github.com/plandes/zotsite
Project-URL: Documentation, https://plandes.github.io/zotsite
Project-URL: Repository, https://github.com/plandes/zotsite.git
Project-URL: Issues, https://github.com/plandes/zotsite/issues
Project-URL: Changelog, https://github.com/plandes/zotsite/blob/master/CHANGELOG.md
Author-email: Paul Landes <landes@mailc.net>
License: MIT
Keywords: academia,papers,web,zotero
Requires-Python: <3.15,>=3.11
Requires-Dist: zensols-db~=1.5.0
